{
  "projects": [
    {
      "id": "663ffa6f-3d5c-4aae-97eb-22818fcaa37f",
      "name": "kripto",
      "description": "kripto App"
    },
    {
      "id": "763ffa6f-3d5c-4aae-97eb-22818fcaa37f",
      "name": "demoin",
      "description": "demoin App"
    },
    {
      "id": "81286ff7-d3b9-4544-8057-4446a08eb89d",
      "name": "momo",
      "description": "momo"
    },
    {
      "id": "5c368bd4-1a52-406c-be16-5670946fab2a",
      "name": "mimi",
      "description": "mimi"
    }
  ],
  "templates": []
}